<xml>
  <navigation type="simple" backgroundColor="" backgroundImage="" contentOverlap="" itemsPosition="" textStyle="" textSize="" textFont="" iosStyleNavigation="">
    <items>
      <item icon="icon-menu.png" text="tab1" textColor="" selectedTextColor="" selectedIcon="" backgroundImage="" selectedBackgroundImage="" backgroundColor="" selectedBackgroundColor="" />
      <item icon="icon-bookmark.png" text="tab2" textColor="" selectedTextColor="" selectedIcon="" backgroundImage="" selectedBackgroundImage="" backgroundColor="" selectedBackgroundColor="" />
      <item icon="icon-global.png" text="tab3" textColor="" selectedTextColor="" selectedIcon="" backgroundImage="" selectedBackgroundImage="" backgroundColor="" selectedBackgroundColor="" />
      <item icon="icon-edit.png" text="tab4" textColor="" selectedTextColor="" selectedIcon="" backgroundImage="" selectedBackgroundImage="" backgroundColor="" selectedBackgroundColor="" />
    </items>
  </navigation>
  <targetplatform simulator="Nexus4">Android</targetplatform>
  <template price="199.99" id="CholiWater" scaleWebPagesToBaseResolution="false" isUniversalApp="false" topadtype="none" bottomadtype="admob" globalLogo="" />
  <prop id="appname" title="App Name">dCholiWater1</prop>
  <prop id="tab1text" title="Tab1 Text">tab1</prop>
  <prop id="tab1icon" title="Tab1 Icon">cover.png</prop>
  <prop id="tab2text" title="Tab2 Text">tab2</prop>
  <prop id="tab2icon" title="Tab2 Icon">index.png</prop>
  <prop id="tab3text" title="Tab3 Text">tab3</prop>
  <prop id="tab3icon" title="Tab3 Icon">content.png</prop>
  <prop id="tab4text" title="Tab4 Text">tab4</prop>
  <prop id="tab4icon" title="Tab4 Icon">coffee.png</prop>
  <planname>Basic</planname>
  <page id="tab2.html" type="html" transition="" slidepageid="" slidetransition="" hasreviews="no" hassend="no" hasfields="no" topad="no" bottomad="no" topadtype="none" bottomadtype="admob" dynamicdata="false" jsonurl="" hasreviewhtmlkey="no" kind="html" title="" logo="" shownavbar="yes" zoomEnabled="false" loadWebUrlsInSameWebView="false" backgroundColor="" />
  <file id="appStyles.xml" newsfile="yes">
  </file>
  <appStoreProperties>
    <recentChanges>
    </recentChanges>
    <reviewContact />
    <reviewDemoAccount username="mmbw0qmJdpbWs0YWna+wUw==" password="mmbw0qmJdpbWs0YWna+wUw==" />
    <primaryLanguage>6</primaryLanguage>
    <privacyPolicy url="http://" />
    <supportUrl>http://</supportUrl>
    <marketingUrl>http://</marketingUrl>
    <publisherReviewAppleID>mmbw0qmJdpbWs0YWna+wUw==</publisherReviewAppleID>
    <publisherReviewNotes>mmbw0qmJdpbWs0YWna+wUw==</publisherReviewNotes>
    <copyright>mmbw0qmJdpbWs0YWna+wUw==</copyright>
  </appStoreProperties>
  <primarycat>-1</primarycat>
  <secondarycat>-1</secondarycat>
  <gameSubcategory1>0</gameSubcategory1>
  <gameSubcategory2>0</gameSubcategory2>
  <magazineSubcategory1>0</magazineSubcategory1>
  <magazineSubcategory2>0</magazineSubcategory2>
  <keywords>
  </keywords>
  <androidC2DM enabled="true" altEnabled="false" />
  <androidpermissions>
    <permission name="android.permission.INTERNET" enabled="true" />
    <permission name="android.permission.ACCESS_COARSE_LOCATION" enabled="true" />
    <permission name="android.permission.ACCESS_FINE_LOCATION" enabled="true" />
    <permission name="android.permission.WRITE_EXTERNAL_STORAGE" enabled="true" />
    <permission name="android.permission.ACCESS_NETWORK_STATE" enabled="true" />
    <permission name="android.permission.READ_PHONE_STATE" enabled="true" />
    <permission name="android.permission.RECORD_AUDIO" enabled="true" />
    <permission name="android.permission.CAMERA" enabled="true" />
    <permission name="android.permission.VIBRATE" enabled="false" />
    <permission name="android.permission.ACCESS_LOCATION_EXTRA_COMMANDS" enabled="false" />
    <permission name="android.permission.RECEIVE_SMS" enabled="false" />
    <permission name="android.permission.RECORD_VIDEO" enabled="false" />
    <permission name="android.permission.MODIFY_AUDIO_SETTINGS" enabled="false" />
    <permission name="android.permission.READ_CONTACTS" enabled="false" />
    <permission name="android.permission.WRITE_CONTACTS" enabled="false" />
    <permission name="android.permission.GET_ACCOUNTS" enabled="false" />
    <permission name="android.permission.BROADCAST_STICKY" enabled="false" />
  </androidpermissions>
  <androidversion>1.0</androidversion>
  <androidversioncode>1</androidversioncode>
  <androidbundlename>larrydelaney.choliwater</androidbundlename>
  <androidshortappname>CholiWater</androidshortappname>
  <syncenabled>true</syncenabled>
  <rotationapp>true</rotationapp>
  <restrictedaccess>
    <feature id="announcements" enabled="true" />
    <feature id="calendar" enabled="true" />
    <feature id="coupon" enabled="true" />
    <feature id="geofences" enabled="true" />
    <feature id="loyalty" enabled="true" />
    <feature id="map" enabled="true" />
    <feature id="productorder" enabled="true" />
    <feature id="pushnotifications" enabled="true" />
    <feature id="Booking" enabled="true" />
    <feature id="pnTopicSubscription" enabled="true" />
    <feature id="loginregister" enabled="true" />
  </restrictedaccess>
  <rateapp appleid="" rateatlaunch="no" rateatrelaunch="no" message="" cancelmessage="" remindmessage="" actionmessage="" />
  <ads allowUsingAdvertisingId="false" />
  <admobpublisher id="ca-app-pub-2795231365031599/9104310278" interstitialUnitId="ca-app-pub-2795231365031599/4339068751" />
  <doubleclickpublisher unitId="" />
  <pollfish apiKey="" padding="0" position="na" />
  <revmobappid id="-" />
  <airpush appId="" apiKey="" interstitialAdType="" />
  <scads refreshRate="30" />
  <googleanalyticsid id="" />
  <localizablelanguage value="en" />
  <paypalappid id="" />
  <dropboxapp dropboxapikey="" />
  <fbapp apikey="" />
  <androidAppLicensing enabled="false" publicKey="" />
  <apkExpansionFiles enabled="false" />
  <androidInAppBilling enabled="false" />
  <android installLocation="auto" />
  <pdftron licenseKey="" />
  <webView bouncesEnabled="false" hideLoadingAnimation="false" externalSiteZoomEnabled="true" />
  <sharepointclient url="" username="" password="" />
  <appstorelink>
  </appstorelink>
  <googleMaps androidApiV2Key="" />
  <baiduMaps baiduMapsApiKeyAndroid="" baiduMapsApiKeyiOS="" />
  <webapp statusBarStyle="default" iconsStyle="precomposed" offlineModeEnabled="false" inAppLinks="false" />
  <locationServices>
    <inUseDescription>
    </inUseDescription>
    <alwaysDescription>
    </alwaysDescription>
  </locationServices>
  <inAppSettings />
  <hostedresources>
  </hostedresources>
  <page id="index.html" type="html" title="" logo="" transition="NONE" slidepageid="none" slidetransition="slide" hasreviews="no" hassend="no" hasfields="no" topadtype="inherited" bottomadtype="admob" dynamicdata="false" jsonurl="" shownavbar="yes" zoomEnabled="false" loadWebUrlsInSameWebView="false" backgroundColor="" kind="html" />
  <healthKitServices>
    <healthShareUsage>
    </healthShareUsage>
    <healthUpdateUsage>
    </healthUpdateUsage>
  </healthKitServices>
  <cameraServices>
    <cameraUsageDescription>
    </cameraUsageDescription>
  </cameraServices>
  <photoLibraryServices>
    <photoLibraryUsageDescription>
    </photoLibraryUsageDescription>
  </photoLibraryServices>
  <microphoneServices>
    <microphoneUsageDescription>
    </microphoneUsageDescription>
  </microphoneServices>
</xml>